{
    "category":  "ENTITY",
    "guid":  "a6076ab9-fe6f-168e-9ef2-b65327d2631c",
    "createdBy":  "admin",
    "updatedBy":  "admin",
    "createTime":  1652152670004,
    "updateTime":  1652152673125,
    "version":  2,
    "name":  "hive_column_lineage",
    "description":  "hive_column_lineage",
    "typeVersion":  "1.1",
    "serviceType":  "hive",
    "lastModifiedTS":  "2",
    "attributeDefs":  [
                          {
                              "name":  "depenendencyType",
                              "typeName":  "string",
                              "isOptional":  false,
                              "cardinality":  "SINGLE",
                              "valuesMinCount":  1,
                              "valuesMaxCount":  1,
                              "isUnique":  false,
                              "isIndexable":  false,
                              "includeInNotification":  false
                          },
                          {
                              "name":  "expression",
                              "typeName":  "string",
                              "isOptional":  true,
                              "cardinality":  "SINGLE",
                              "valuesMinCount":  0,
                              "valuesMaxCount":  1,
                              "isUnique":  false,
                              "isIndexable":  false,
                              "includeInNotification":  false
                          }
                      ],
    "superTypes":  [
                       "Process"
                   ],
    "subTypes":  [

                 ],
    "relationshipAttributeDefs":  [
                                      {
                                          "name":  "outputs",
                                          "typeName":  "array\u003cDataSet\u003e",
                                          "isOptional":  true,
                                          "cardinality":  "SET",
                                          "valuesMinCount":  0,
                                          "valuesMaxCount":  2147483647,
                                          "isUnique":  false,
                                          "isIndexable":  false,
                                          "includeInNotification":  false,
                                          "relationshipTypeName":  "process_dataset_outputs",
                                          "isLegacyAttribute":  true
                                      },
                                      {
                                          "name":  "inputs",
                                          "typeName":  "array\u003cDataSet\u003e",
                                          "isOptional":  true,
                                          "cardinality":  "SET",
                                          "valuesMinCount":  0,
                                          "valuesMaxCount":  2147483647,
                                          "isUnique":  false,
                                          "isIndexable":  false,
                                          "includeInNotification":  false,
                                          "relationshipTypeName":  "dataset_process_inputs",
                                          "isLegacyAttribute":  true
                                      },
                                      {
                                          "name":  "query",
                                          "typeName":  "hive_process",
                                          "isOptional":  false,
                                          "cardinality":  "SINGLE",
                                          "valuesMinCount":  -1,
                                          "valuesMaxCount":  -1,
                                          "isUnique":  false,
                                          "isIndexable":  false,
                                          "includeInNotification":  false,
                                          "relationshipTypeName":  "hive_process_column_lineage",
                                          "isLegacyAttribute":  true
                                      },
                                      {
                                          "name":  "meanings",
                                          "typeName":  "array\u003cAtlasGlossaryTerm\u003e",
                                          "isOptional":  true,
                                          "cardinality":  "SET",
                                          "valuesMinCount":  -1,
                                          "valuesMaxCount":  -1,
                                          "isUnique":  false,
                                          "isIndexable":  false,
                                          "includeInNotification":  false,
                                          "relationshipTypeName":  "AtlasGlossarySemanticAssignment",
                                          "isLegacyAttribute":  false
                                      }
                                  ],
    "businessAttributeDefs":  {

                              }
}
