{
    "category":  "ENTITY",
    "guid":  "60e44bae-3728-eb1c-3da2-eb17d7f24d18",
    "createdBy":  "admin",
    "updatedBy":  "admin",
    "createTime":  1652152697595,
    "updateTime":  1652152697595,
    "version":  1,
    "name":  "parquet_schema",
    "description":  "parquet_schema",
    "typeVersion":  "1.0",
    "lastModifiedTS":  "1",
    "attributeDefs":  [

                      ],
    "superTypes":  [
                       "schema"
                   ],
    "subTypes":  [

                 ],
    "relationshipAttributeDefs":  [
                                      {
                                          "name":  "schema",
                                          "typeName":  "array\u003cavro_schema\u003e",
                                          "isOptional":  true,
                                          "cardinality":  "SET",
                                          "valuesMinCount":  -1,
                                          "valuesMaxCount":  -1,
                                          "isUnique":  false,
                                          "isIndexable":  false,
                                          "includeInNotification":  false,
                                          "relationshipTypeName":  "avro_schema_associatedEntities",
                                          "isLegacyAttribute":  false
                                      },
                                      {
                                          "name":  "inputToProcesses",
                                          "typeName":  "array\u003cProcess\u003e",
                                          "isOptional":  true,
                                          "cardinality":  "SET",
                                          "valuesMinCount":  -1,
                                          "valuesMaxCount":  -1,
                                          "isUnique":  false,
                                          "isIndexable":  false,
                                          "includeInNotification":  false,
                                          "relationshipTypeName":  "dataset_process_inputs",
                                          "isLegacyAttribute":  false
                                      },
                                      {
                                          "name":  "pipeline",
                                          "typeName":  "spark_ml_pipeline",
                                          "isOptional":  true,
                                          "cardinality":  "SINGLE",
                                          "valuesMinCount":  -1,
                                          "valuesMaxCount":  -1,
                                          "isUnique":  false,
                                          "isIndexable":  false,
                                          "includeInNotification":  false,
                                          "relationshipTypeName":  "spark_ml_pipeline_dataset",
                                          "isLegacyAttribute":  false
                                      },
                                      {
                                          "name":  "columns",
                                          "typeName":  "array\u003cparquet_schema_element\u003e",
                                          "isOptional":  true,
                                          "cardinality":  "SET",
                                          "valuesMinCount":  -1,
                                          "valuesMaxCount":  -1,
                                          "isUnique":  false,
                                          "isIndexable":  false,
                                          "includeInNotification":  false,
                                          "constraints":  [
                                                              {
                                                                  "type":  "ownedRef"
                                                              }
                                                          ],
                                          "relationshipTypeName":  "parquet_schema_columns",
                                          "isLegacyAttribute":  false
                                      },
                                      {
                                          "name":  "relatedDataSets",
                                          "typeName":  "array\u003cDataSet\u003e",
                                          "isOptional":  true,
                                          "cardinality":  "SET",
                                          "valuesMinCount":  -1,
                                          "valuesMaxCount":  -1,
                                          "isUnique":  false,
                                          "isIndexable":  false,
                                          "includeInNotification":  false,
                                          "relationshipTypeName":  "dataset_attached_schemas",
                                          "isLegacyAttribute":  false
                                      },
                                      {
                                          "name":  "model",
                                          "typeName":  "spark_ml_model",
                                          "isOptional":  true,
                                          "cardinality":  "SINGLE",
                                          "valuesMinCount":  -1,
                                          "valuesMaxCount":  -1,
                                          "isUnique":  false,
                                          "isIndexable":  false,
                                          "includeInNotification":  false,
                                          "relationshipTypeName":  "spark_ml_model_dataset",
                                          "isLegacyAttribute":  false
                                      },
                                      {
                                          "name":  "attachedSchema",
                                          "typeName":  "array\u003cschema\u003e",
                                          "isOptional":  true,
                                          "cardinality":  "SET",
                                          "valuesMinCount":  -1,
                                          "valuesMaxCount":  -1,
                                          "isUnique":  false,
                                          "isIndexable":  false,
                                          "includeInNotification":  false,
                                          "relationshipTypeName":  "dataset_attached_schemas",
                                          "isLegacyAttribute":  false
                                      },
                                      {
                                          "name":  "meanings",
                                          "typeName":  "array\u003cAtlasGlossaryTerm\u003e",
                                          "isOptional":  true,
                                          "cardinality":  "SET",
                                          "valuesMinCount":  -1,
                                          "valuesMaxCount":  -1,
                                          "isUnique":  false,
                                          "isIndexable":  false,
                                          "includeInNotification":  false,
                                          "relationshipTypeName":  "AtlasGlossarySemanticAssignment",
                                          "isLegacyAttribute":  false
                                      },
                                      {
                                          "name":  "outputFromProcesses",
                                          "typeName":  "array\u003cProcess\u003e",
                                          "isOptional":  true,
                                          "cardinality":  "SET",
                                          "valuesMinCount":  -1,
                                          "valuesMaxCount":  -1,
                                          "isUnique":  false,
                                          "isIndexable":  false,
                                          "includeInNotification":  false,
                                          "relationshipTypeName":  "process_dataset_outputs",
                                          "isLegacyAttribute":  false
                                      },
                                      {
                                          "name":  "tabular_schema",
                                          "typeName":  "tabular_schema",
                                          "isOptional":  true,
                                          "cardinality":  "SINGLE",
                                          "valuesMinCount":  -1,
                                          "valuesMaxCount":  -1,
                                          "isUnique":  false,
                                          "isIndexable":  false,
                                          "includeInNotification":  false,
                                          "relationshipTypeName":  "tabular_schema_datasets",
                                          "isLegacyAttribute":  false
                                      }
                                  ],
    "businessAttributeDefs":  {

                              }
}
